[
  {
    "text": "",
    "selector": "#hs-web-interactives-top-anchor",
    "boundingBox": {
      "x": 0,
      "y": 0,
      "width": 1280,
      "height": 720,
      "top": 0,
      "right": 1280,
      "bottom": 720,
      "left": 0
    }
  },
  {
    "text": "",
    "selector": "body.iccnonpremium > div > div.v-application.v-application--is-ltr > div.v-application--wrap > div.v-overlay.theme--dark",
    "boundingBox": {
      "x": 0,
      "y": 0,
      "width": 1280,
      "height": 720,
      "top": 0,
      "right": 1280,
      "bottom": 720,
      "left": 0
    }
  },
  {
    "text": "",
    "selector": "body.iccnonpremium > div > div.v-application.v-application--is-ltr > div.v-application--wrap > div.v-snack.v-snack--has-background",
    "boundingBox": {
      "x": 0,
      "y": 0,
      "width": 1280,
      "height": 720,
      "top": 0,
      "right": 1280,
      "bottom": 720,
      "left": 0
    }
  },
  {
    "text": "",
    "selector": "body.iccnonpremium > div > div.v-application.v-application--is-ltr > div.v-application--wrap > div.v-snack.v-snack--has-background",
    "boundingBox": {
      "x": 0,
      "y": 0,
      "width": 1280,
      "height": 720,
      "top": 0,
      "right": 1280,
      "bottom": 720,
      "left": 0
    }
  },
  {
    "text": "menu\nMenu\n​\nSearch Digital Codes\nSubscribe\nSign In",
    "selector": "#navigation-app",
    "boundingBox": {
      "x": 0,
      "y": 0,
      "width": 1280,
      "height": 64,
      "top": 0,
      "right": 1280,
      "bottom": 64,
      "left": 0
    }
  },
  {
    "text": "We use essential cookies to make our site work. With your consent, we may also use non-essential cookies to improve user experience, personalize content, and analyze website traffic. For these reasons, we may share your site usage data with our analytics partners. By clicking “Accept,” you agree to our website's cookie use as described in our Cookie Policy. You can change your cookie settings at any time by clicking “Preferences.”\nPreferences\nDecline\nAccept",
    "selector": "body.iccnonpremium > div > div > div.termly-styles-root-b0aebb.termly-styles-termly-banner-e1ed59",
    "boundingBox": {
      "x": 0,
      "y": 556,
      "width": 1280,
      "height": 144,
      "top": 556,
      "right": 1280,
      "bottom": 700,
      "left": 0
    }
  }
]