{
    "name": "auto_FR_es.fr_uwu",
    "cosmetic": false,
    "_metadata": {
        "vendorUrl": "http://www.es.fr/"
    },
    "runContext": {
        "main": true,
        "frame": false,
        "urlPattern": "^https?://(www\\.)?es\\.fr/"
    },
    "prehideSelectors": [],
    "detectCmp": [
        {
            "exists": "body > div:not([id]) > div:nth-child(2):not([id]) > main:nth-child(2):not([id]) > div:nth-child(2):not([id]) > div:nth-child(2)#block-es-cookiesui > div#cookiesjsr > div:not([id]) > div:not([id]) > div:nth-child(2):not([id]) > button:nth-child(2):not([id])"
        }
    ],
    "detectPopup": [
        {
            "visible": "body > div:not([id]) > div:nth-child(2):not([id]) > main:nth-child(2):not([id]) > div:nth-child(2):not([id]) > div:nth-child(2)#block-es-cookiesui > div#cookiesjsr > div:not([id]) > div:not([id]) > div:nth-child(2):not([id]) > button:nth-child(2):not([id])"
        }
    ],
    "optIn": [],
    "optOut": [
        {
            "wait": 500
        },
        {
            "waitForThenClick": "body > div:not([id]) > div:nth-child(2):not([id]) > main:nth-child(2):not([id]) > div:nth-child(2):not([id]) > div:nth-child(2)#block-es-cookiesui > div#cookiesjsr > div:not([id]) > div:not([id]) > div:nth-child(2):not([id]) > button:nth-child(2):not([id])",
            "comment": "TOUT REFUSER"
        }
    ],
    "test": [
        {
            "waitForVisible": "body > div:not([id]) > div:nth-child(2):not([id]) > main:nth-child(2):not([id]) > div:nth-child(2):not([id]) > div:nth-child(2)#block-es-cookiesui > div#cookiesjsr > div:not([id]) > div:not([id]) > div:nth-child(2):not([id]) > button:nth-child(2):not([id])",
            "timeout": 1000,
            "check": "none"
        }
    ]
}
