{
    "name": "auto_CA_komoot.com_rde",
    "cosmetic": false,
    "runContext": {
        "main": true,
        "frame": false,
        "urlPattern": "^https?://(www\\.)?komoot\\.com/"
    },
    "prehideSelectors": [],
    "detectCmp": [
        {
            "exists": "body > div#pageMountNode > div:not([id]) > dialog:nth-child(6):not([id]) > div:not([id]) > footer:nth-child(4):not([id]) > button:nth-child(3):not([id])"
        }
    ],
    "detectPopup": [
        {
            "visible": "body > div#pageMountNode > div:not([id]) > dialog:nth-child(6):not([id]) > div:not([id]) > footer:nth-child(4):not([id]) > button:nth-child(3):not([id])"
        }
    ],
    "optIn": [],
    "optOut": [
        {
            "wait": 500
        },
        {
            "waitForThenClick": "body > div#pageMountNode > div:not([id]) > dialog:nth-child(6):not([id]) > div:not([id]) > footer:nth-child(4):not([id]) > button:nth-child(3):not([id])",
            "comment": "Refuse"
        }
    ],
    "test": [
        {
            "waitForVisible": "body > div#pageMountNode > div:not([id]) > dialog:nth-child(6):not([id]) > div:not([id]) > footer:nth-child(4):not([id]) > button:nth-child(3):not([id])",
            "timeout": 1000,
            "check": "none"
        }
    ]
}
