{
    "name": "auto_US_newsbusters.org_kna",
    "vendorUrl": "https://www.newsbusters.org/",
    "cosmetic": false,
    "runContext": {
        "main": true,
        "frame": false,
        "urlPattern": "^https?://(www\\.)?newsbusters\\.org/"
    },
    "prehideSelectors": [],
    "detectCmp": [
        {
            "exists": "body > div:not([id]) > div#page-wrapper > div#page > header:nth-child(1)#header > div#block-cookies-ui-block > div:not([id]) > div#cookiesjsr > div:not([id]) > div:not([id]) > div:nth-child(2):not([id]) > button:nth-child(2):not([id])"
        }
    ],
    "detectPopup": [
        {
            "visible": "body > div:not([id]) > div#page-wrapper > div#page > header:nth-child(1)#header > div#block-cookies-ui-block > div:not([id]) > div#cookiesjsr > div:not([id]) > div:not([id]) > div:nth-child(2):not([id]) > button:nth-child(2):not([id])"
        }
    ],
    "optIn": [],
    "optOut": [
        {
            "wait": 500
        },
        {
            "waitForThenClick": "body > div:not([id]) > div#page-wrapper > div#page > header:nth-child(1)#header > div#block-cookies-ui-block > div:not([id]) > div#cookiesjsr > div:not([id]) > div:not([id]) > div:nth-child(2):not([id]) > button:nth-child(2):not([id])",
            "comment": "DENY ALL"
        }
    ],
    "test": [
        {
            "waitForVisible": "body > div:not([id]) > div#page-wrapper > div#page > header:nth-child(1)#header > div#block-cookies-ui-block > div:not([id]) > div#cookiesjsr > div:not([id]) > div:not([id]) > div:nth-child(2):not([id]) > button:nth-child(2):not([id])",
            "timeout": 1000,
            "check": "none"
        }
    ]
}
