{
    "name": "auto_FR_jeunes.nouvelle-aquitaine.fr_hcs",
    "cosmetic": false,
    "_metadata": {
        "vendorUrl": "http://jeunes.nouvelle-aquitaine.fr/"
    },
    "runContext": {
        "main": true,
        "frame": false,
        "urlPattern": "^https?://(www\\.)?jeunes\\.nouvelle-aquitaine\\.fr/"
    },
    "prehideSelectors": [],
    "detectCmp": [
        {
            "exists": "body > div#naq_cookie_container > div#sliding-popup > div:not([id]) > div:nth-child(3):not([id]) > button:nth-child(1)#btn-cookie-rechFormModifier"
        }
    ],
    "detectPopup": [
        {
            "visible": "body > div#naq_cookie_container > div#sliding-popup > div:not([id]) > div:nth-child(3):not([id]) > button:nth-child(1)#btn-cookie-rechFormModifier"
        }
    ],
    "optIn": [],
    "optOut": [
        {
            "wait": 500
        },
        {
            "waitForThenClick": "body > div#naq_cookie_container > div#sliding-popup > div:not([id]) > div:nth-child(3):not([id]) > button:nth-child(1)#btn-cookie-rechFormModifier",
            "comment": "Je refuse\nl'utilisation de cookies"
        }
    ],
    "test": [
        {
            "waitForVisible": "body > div#naq_cookie_container > div#sliding-popup > div:not([id]) > div:nth-child(3):not([id]) > button:nth-child(1)#btn-cookie-rechFormModifier",
            "timeout": 1000,
            "check": "none"
        }
    ]
}
