{
    "name": "auto_GB_handbook.fca.org.uk_0",
    "cosmetic": false,
    "runContext": {
        "main": true,
        "frame": false,
        "urlPattern": "^https?://(www\\.)?handbook\\.fca\\.org\\.uk/"
    },
    "prehideSelectors": [],
    "detectCmp": [
        {
            "exists": "body > div:not([id]) > div:not([id]) > div:not([id]) > div:nth-child(3):not([id]) > form:nth-child(2):not([id]) > button:nth-child(2)#cookieConsentRejectAll"
        }
    ],
    "detectPopup": [
        {
            "visible": "body > div:not([id]) > div:not([id]) > div:not([id]) > div:nth-child(3):not([id]) > form:nth-child(2):not([id]) > button:nth-child(2)#cookieConsentRejectAll"
        }
    ],
    "optIn": [],
    "optOut": [
        {
            "wait": 500
        },
        {
            "waitForThenClick": "body > div:not([id]) > div:not([id]) > div:not([id]) > div:nth-child(3):not([id]) > form:nth-child(2):not([id]) > button:nth-child(2)#cookieConsentRejectAll",
            "comment": "Reject additional cookies"
        }
    ],
    "test": [
        {
            "waitForVisible": "body > div:not([id]) > div:not([id]) > div:not([id]) > div:nth-child(3):not([id]) > form:nth-child(2):not([id]) > button:nth-child(2)#cookieConsentRejectAll",
            "timeout": 1000,
            "check": "none"
        }
    ]
}
