{
    "name": "auto_CH_afv.ch_qwe",
    "cosmetic": false,
    "_metadata": {
        "vendorUrl": "http://www.afv.ch/"
    },
    "runContext": {
        "main": true,
        "frame": false,
        "urlPattern": "^https?://(www\\.)?afv\\.ch/"
    },
    "prehideSelectors": [],
    "detectCmp": [
        {
            "exists": "body > div#qc-cmp2-container > div#qc-cmp2-main > div:not([id]) > div#qc-cmp2-ui > div:nth-child(2):not([id]) > div:not([id]) > button:nth-child(2)#disagree-btn"
        }
    ],
    "detectPopup": [
        {
            "visible": "body > div#qc-cmp2-container > div#qc-cmp2-main > div:not([id]) > div#qc-cmp2-ui > div:nth-child(2):not([id]) > div:not([id]) > button:nth-child(2)#disagree-btn"
        }
    ],
    "optIn": [],
    "optOut": [
        {
            "wait": 500
        },
        {
            "waitForThenClick": "body > div#qc-cmp2-container > div#qc-cmp2-main > div:not([id]) > div#qc-cmp2-ui > div:nth-child(2):not([id]) > div:not([id]) > button:nth-child(2)#disagree-btn",
            "comment": "ABLEHNEN"
        }
    ],
    "test": [
        {
            "waitForVisible": "body > div#qc-cmp2-container > div#qc-cmp2-main > div:not([id]) > div#qc-cmp2-ui > div:nth-child(2):not([id]) > div:not([id]) > button:nth-child(2)#disagree-btn",
            "timeout": 1000,
            "check": "none"
        }
    ]
}
