{
    "name": "auto_DE_emedienbayern.onleihe.de_3ds",
    "cosmetic": false,
    "_metadata": {
        "vendorUrl": "http://emedienbayern.onleihe.de/"
    },
    "runContext": {
        "main": true,
        "frame": false,
        "urlPattern": "^https?://(www\\.)?emedienbayern\\.onleihe\\.de/"
    },
    "prehideSelectors": [],
    "detectCmp": [
        {
            "exists": "body > div:not([id]) > div:not([id]) > div:nth-child(2):not([id]) > div:not([id]) > div:not([id]) > div:not([id]) > div:not([id]) > div:not([id]) > div:not([id]) > div:nth-child(3):not([id]) > div:nth-child(1):not([id]) > button:not([id])[data-testid=\"cookiesOnlyRequiredButton\"]"
        }
    ],
    "detectPopup": [
        {
            "visible": "body > div:not([id]) > div:not([id]) > div:nth-child(2):not([id]) > div:not([id]) > div:not([id]) > div:not([id]) > div:not([id]) > div:not([id]) > div:not([id]) > div:nth-child(3):not([id]) > div:nth-child(1):not([id]) > button:not([id])[data-testid=\"cookiesOnlyRequiredButton\"]"
        }
    ],
    "optIn": [],
    "optOut": [
        {
            "wait": 500
        },
        {
            "waitForThenClick": "body > div:not([id]) > div:not([id]) > div:nth-child(2):not([id]) > div:not([id]) > div:not([id]) > div:not([id]) > div:not([id]) > div:not([id]) > div:not([id]) > div:nth-child(3):not([id]) > div:nth-child(1):not([id]) > button:not([id])[data-testid=\"cookiesOnlyRequiredButton\"]",
            "comment": "Nur Notwendige"
        }
    ],
    "test": [
        {
            "waitForVisible": "body > div:not([id]) > div:not([id]) > div:nth-child(2):not([id]) > div:not([id]) > div:not([id]) > div:not([id]) > div:not([id]) > div:not([id]) > div:not([id]) > div:nth-child(3):not([id]) > div:nth-child(1):not([id]) > button:not([id])[data-testid=\"cookiesOnlyRequiredButton\"]",
            "timeout": 1000,
            "check": "none"
        }
    ]
}
