{
    "name": "auto_NL_norah.eu_iv4",
    "cosmetic": false,
    "_metadata": {
        "vendorUrl": "http://www.norah.eu/"
    },
    "runContext": {
        "main": true,
        "frame": false,
        "urlPattern": "^https?://(www\\.)?norah\\.eu/"
    },
    "prehideSelectors": [],
    "detectCmp": [
        {
            "exists": "body > div:not([id]) > div:not([id]) > div:not([id]) > div:nth-child(1):not([id]) > div:nth-child(2):not([id]) > span:nth-child(3):not([id]) > button:not([id])"
        }
    ],
    "detectPopup": [
        {
            "visible": "body > div:not([id]) > div:not([id]) > div:not([id]) > div:nth-child(1):not([id]) > div:nth-child(2):not([id]) > span:nth-child(3):not([id]) > button:not([id])"
        }
    ],
    "optIn": [],
    "optOut": [
        {
            "wait": 500
        },
        {
            "waitForThenClick": "body > div:not([id]) > div:not([id]) > div:not([id]) > div:nth-child(1):not([id]) > div:nth-child(2):not([id]) > span:nth-child(3):not([id]) > button:not([id])",
            "comment": "weiger"
        }
    ],
    "test": [
        {
            "waitForVisible": "body > div:not([id]) > div:not([id]) > div:not([id]) > div:nth-child(1):not([id]) > div:nth-child(2):not([id]) > span:nth-child(3):not([id]) > button:not([id])",
            "timeout": 1000,
            "check": "none"
        }
    ]
}
