{
    "name": "auto_NL_fox.nl_vzi",
    "cosmetic": false,
    "_metadata": {
        "vendorUrl": "http://www.fox.nl/"
    },
    "runContext": {
        "main": true,
        "frame": false,
        "urlPattern": "^https?://(www\\.)?fox\\.nl/"
    },
    "prehideSelectors": [],
    "detectCmp": [
        {
            "exists": "body > div#__next > div:not([id]) > div:nth-child(1):not([id]) > div:not([id]) > div:not([id]) > div:nth-child(6):not([id]) > button:nth-child(3):not([id])"
        }
    ],
    "detectPopup": [
        {
            "visible": "body > div#__next > div:not([id]) > div:nth-child(1):not([id]) > div:not([id]) > div:not([id]) > div:nth-child(6):not([id]) > button:nth-child(3):not([id])"
        }
    ],
    "optIn": [],
    "optOut": [
        {
            "wait": 500
        },
        {
            "waitForThenClick": "body > div#__next > div:not([id]) > div:nth-child(1):not([id]) > div:not([id]) > div:not([id]) > div:nth-child(6):not([id]) > button:nth-child(3):not([id])",
            "comment": "Weigeren"
        }
    ],
    "test": [
        {
            "waitForVisible": "body > div#__next > div:not([id]) > div:nth-child(1):not([id]) > div:not([id]) > div:not([id]) > div:nth-child(6):not([id]) > button:nth-child(3):not([id])",
            "timeout": 1000,
            "check": "none"
        }
    ]
}
