{
    "name": "auto_NL_pytorch.org_3bl",
    "cosmetic": false,
    "_metadata": {
        "vendorUrl": "http://pytorch.org/"
    },
    "runContext": {
        "main": true,
        "frame": false,
        "urlPattern": "^https?://(www\\.)?pytorch\\.org/"
    },
    "prehideSelectors": [],
    "detectCmp": [
        {
            "exists": "body > div:not([id]) > div:nth-child(2)#f0a2e898-df4a-47b5-ac2b-9b62bbeebc10 > div:nth-child(3):not([id]) > button:nth-child(3):not([id])"
        }
    ],
    "detectPopup": [
        {
            "visible": "body > div:not([id]) > div:nth-child(2)#f0a2e898-df4a-47b5-ac2b-9b62bbeebc10 > div:nth-child(3):not([id]) > button:nth-child(3):not([id])"
        }
    ],
    "optIn": [],
    "optOut": [
        {
            "wait": 500
        },
        {
            "waitForThenClick": "body > div:not([id]) > div:nth-child(2)#f0a2e898-df4a-47b5-ac2b-9b62bbeebc10 > div:nth-child(3):not([id]) > button:nth-child(3):not([id])",
            "comment": "Reject Non-Essential"
        }
    ],
    "test": [
        {
            "waitForVisible": "body > div:not([id]) > div:nth-child(2)#f0a2e898-df4a-47b5-ac2b-9b62bbeebc10 > div:nth-child(3):not([id]) > button:nth-child(3):not([id])",
            "timeout": 1000,
            "check": "none"
        }
    ]
}
